midi_diff/__init__.py
midi_diff/__main__.py
midi_diff/cli/__init__.py
midi_diff/cli/__main__.py
midi_diff/cli/completions.py
midi_diff/cli/docs.py
midi_diff/cli/main.py
midi_diff/cli/version.py
midi_diff/core.py
midi_diff/midi_utils.py
midi_diff-1.1.0.dist-info/LICENSE.md
midi_diff-1.1.0.dist-info/METADATA
midi_diff-1.1.0.dist-info/WHEEL
midi_diff-1.1.0.dist-info/entry_points.txt
midi_diff-1.1.0.dist-info/RECORD
