Metadata-Version: 2.1
Name: midi-diff
Version: 1.1.0
Summary: Output the differences between two MIDI files, using the command-line.
License: MIT
Author: Taylor-Jayde Blackstone
Author-email: t.blackstone@inspyre.tech
Requires-Python: >=3.11,<4.0
Classifier: Development Status :: 5 - Production/Stable
Classifier: Environment :: Console
Classifier: Intended Audience :: Developers
Classifier: License :: OSI Approved :: MIT License
Classifier: Operating System :: Microsoft :: Windows
Classifier: Operating System :: OS Independent
Classifier: Operating System :: POSIX :: Linux
Classifier: Programming Language :: Python :: 3
Classifier: Programming Language :: Python :: 3.11
Classifier: Programming Language :: Python :: 3.12
Classifier: Programming Language :: Python :: 3 :: Only
Classifier: Programming Language :: Python :: 3.13
Classifier: Programming Language :: Python :: Implementation :: CPython
Classifier: Topic :: Multimedia :: Sound/Audio :: MIDI
Classifier: Typing :: Typed
Provides-Extra: cli
Requires-Dist: mido (>=1.3.3,<2.0.0)
Requires-Dist: packaging (>=20.0)
Requires-Dist: rich (>=13.0.0,<14.0.0) ; extra == "cli"
